{"v":"5.6.6","fr":25,"ip":0,"op":32,"w":100,"h":100,"nm":"题库（切框）","ddd":0,"assets":[],"layers":[{"ddd":0,"ind":1,"ty":4,"nm":"“图层 4”轮廓 13","sr":1,"ks":{"o":{"a":0,"k":100,"ix":11},"r":{"a":0,"k":0,"ix":10},"p":{"a":0,"k":[64.553,50.726,0],"ix":2},"a":{"a":0,"k":[34.377,48.521,0],"ix":1},"s":{"a":0,"k":[100,100,100],"ix":6}},"ao":0,"shapes":[{"ty":"gr","it":[{"ind":0,"ty":"sh","ix":1,"ks":{"a":0,"k":{"i":[[0,0],[0,0]],"o":[[0,0],[0,0]],"v":[[24.499,-40.555],[24.499,-40.523]],"c":true},"ix":2},"nm":"路径 1","mn":"ADBE Vector Shape - Group","hd":false},{"ind":1,"ty":"sh","ix":2,"ks":{"a":0,"k":{"i":[[1.687,0],[0.726,0.396],[-1.261,2.312],[-18.557,-4.109],[-0.193,-0.006],[0.021,1.339],[0,0],[0,0],[4.562,-5.564],[0.02,-0.288],[2.635,0.185],[-0.186,2.623],[-14.61,18.07],[-10.2,-0.033],[0,0],[0.037,-4.213],[0,0],[6.593,-0.101],[0.855,0.181],[6.53,-11.972]],"o":[[-0.77,0],[-2.311,-1.261],[7.308,-13.4],[0.121,0.026],[1.328,-0.019],[0,0],[0,0],[-7.192,-0.062],[-12.692,15.697],[-0.191,2.623],[-2.625,-0.186],[0.093,-1.296],[6.414,-7.823],[0,0],[4.266,0.047],[0,0],[0.096,6.522],[-0.873,-0.013],[-9.991,-2.211],[-0.865,1.587]],"v":[[-14.309,48.271],[-16.588,47.688],[-18.49,41.221],[21.628,26.818],[22.117,26.859],[24.499,24.393],[24.499,-38.705],[9.009,-38.705],[-9.519,-30.027],[-24.432,14.613],[-29.527,19.025],[-33.941,13.936],[-16.911,-36.044],[9.039,-48.238],[26.406,-48.238],[34.031,-40.512],[34.031,24.322],[22.251,36.391],[19.615,36.135],[-10.12,45.785]],"c":true},"ix":2},"nm":"路径 2","mn":"ADBE Vector Shape - Group","hd":false},{"ty":"mm","mm":1,"nm":"合并路径 1","mn":"ADBE Vector Filter - Merge","hd":false},{"ty":"fl","c":{"a":0,"k":[0,0,0,1],"ix":4},"o":{"a":0,"k":100,"ix":5},"r":1,"bm":0,"nm":"填充 1","mn":"ADBE Vector Graphic - Fill","hd":false},{"ty":"tr","p":{"a":0,"k":[34.377,48.522],"ix":2},"a":{"a":0,"k":[0,0],"ix":1},"s":{"a":0,"k":[100,100],"ix":3},"r":{"a":0,"k":0,"ix":6},"o":{"a":0,"k":100,"ix":7},"sk":{"a":0,"k":0,"ix":4},"sa":{"a":0,"k":0,"ix":5},"nm":"变换"}],"nm":"组 1","np":4,"cix":2,"bm":0,"ix":1,"mn":"ADBE Vector Group","hd":false}],"ip":0,"op":1,"st":-24,"bm":0},{"ddd":0,"ind":2,"ty":4,"nm":"“图层 6”轮廓 13","sr":1,"ks":{"o":{"a":0,"k":100,"ix":11},"r":{"a":0,"k":0,"ix":10},"p":{"a":0,"k":[35.727,50.728,0],"ix":2},"a":{"a":0,"k":[33.976,48.522,0],"ix":1},"s":{"a":0,"k":[100,100,100],"ix":6}},"ao":0,"shapes":[{"ty":"gr","it":[{"ind":0,"ty":"sh","ix":1,"ks":{"a":0,"k":{"i":[[0,0],[0,0]],"o":[[0,0],[0,0]],"v":[[-24.12,-40.634],[-24.12,-40.589]],"c":true},"ix":2},"nm":"路径 1","mn":"ADBE Vector Shape - Group","hd":false},{"ind":1,"ty":"sh","ix":2,"ks":{"a":0,"k":{"i":[[0.761,0],[0.859,1.6],[9.767,-2.198],[0.889,0.03],[2.194,2.298],[-0.076,3.176],[0,0],[-4.205,0.05],[0,0],[-6.114,-6.842],[-0.095,-1.368],[2.623,-0.186],[0.188,2.624],[13.447,15.384],[6.348,0],[0.075,-0.001],[0,0],[0,0],[-0.254,-0.265],[-0.852,-0.019],[-0.175,0.036],[-7.223,-13.424],[2.317,-1.247]],"o":[[-1.699,0],[-6.43,-11.943],[-0.961,0.197],[-3.186,-0.076],[-2.192,-2.3],[0,0],[-0.049,-4.151],[0,0],[9.232,-0.035],[15.604,17.849],[0.184,2.625],[-2.693,0.201],[-0.021,-0.303],[-4.199,-4.699],[-0.075,0],[0,0],[0,0],[-0.021,0.962],[0.251,0.264],[0.179,-0.002],[18.266,-4.101],[1.247,2.318],[-0.717,0.387]],"v":[[14.112,48.272],[9.911,45.763],[-19.286,36.124],[-22.03,36.382],[-30.366,32.702],[-33.65,24.211],[-33.652,-40.574],[-26.117,-48.237],[-8.609,-48.237],[15.406,-37.616],[33.542,13.937],[29.125,19.025],[24.033,14.607],[8.264,-31.304],[-8.334,-38.706],[-8.56,-38.705],[-24.12,-38.705],[-24.12,24.324],[-23.468,26.121],[-21.816,26.851],[-21.285,26.804],[18.303,41.246],[16.365,47.702]],"c":true},"ix":2},"nm":"路径 2","mn":"ADBE Vector Shape - Group","hd":false},{"ty":"mm","mm":1,"nm":"合并路径 1","mn":"ADBE Vector Filter - Merge","hd":false},{"ty":"fl","c":{"a":0,"k":[0,0,0,1],"ix":4},"o":{"a":0,"k":100,"ix":5},"r":1,"bm":0,"nm":"填充 1","mn":"ADBE Vector Graphic - Fill","hd":false},{"ty":"tr","p":{"a":0,"k":[33.976,48.522],"ix":2},"a":{"a":0,"k":[0,0],"ix":1},"s":{"a":0,"k":[100,100],"ix":3},"r":{"a":0,"k":0,"ix":6},"o":{"a":0,"k":100,"ix":7},"sk":{"a":0,"k":0,"ix":4},"sa":{"a":0,"k":0,"ix":5},"nm":"变换"}],"nm":"组 1","np":4,"cix":2,"bm":0,"ix":1,"mn":"ADBE Vector Group","hd":false}],"ip":0,"op":1,"st":-24,"bm":0},{"ddd":0,"ind":3,"ty":4,"nm":"“图层 5”轮廓 2","sr":1,"ks":{"o":{"a":0,"k":100,"ix":11},"r":{"a":0,"k":0,"ix":10},"p":{"a":1,"k":[{"i":{"x":0.667,"y":1},"o":{"x":0.333,"y":0},"t":-25,"s":[60.719,49.186,0],"to":[-1.894,0,0],"ti":[1.894,0,0]},{"t":-21,"s":[49.352,49.186,0]}],"ix":2},"a":{"a":0,"k":[17.136,5.017,0],"ix":1},"s":{"a":1,"k":[{"i":{"x":[0.667,0.667,0.667],"y":[1,1,1]},"o":{"x":[0.333,0.333,0.333],"y":[0,0,0]},"t":-25,"s":[13.54,100,100]},{"t":-21,"s":[88.156,100,100]}],"ix":6}},"ao":0,"shapes":[{"ty":"gr","it":[{"ind":0,"ty":"sh","ix":1,"ks":{"a":0,"k":{"i":[[2.632,0],[0,0],[0,2.632],[-2.633,0],[0,0],[0,-2.631]],"o":[[0,0],[-2.633,0],[0,-2.631],[0,0],[2.632,0],[0,2.632]],"v":[[12.12,4.766],[-12.12,4.766],[-16.887,-0.001],[-12.12,-4.766],[12.12,-4.766],[16.887,-0.001]],"c":true},"ix":2},"nm":"路径 1","mn":"ADBE Vector Shape - Group","hd":false},{"ty":"fl","c":{"a":0,"k":[0,0,0,1],"ix":4},"o":{"a":0,"k":100,"ix":5},"r":1,"bm":0,"nm":"填充 1","mn":"ADBE Vector Graphic - Fill","hd":false},{"ty":"tr","p":{"a":0,"k":[17.136,5.017],"ix":2},"a":{"a":0,"k":[0,0],"ix":1},"s":{"a":0,"k":[100,100],"ix":3},"r":{"a":0,"k":0,"ix":6},"o":{"a":0,"k":100,"ix":7},"sk":{"a":0,"k":0,"ix":4},"sa":{"a":0,"k":0,"ix":5},"nm":"变换"}],"nm":"组 1","np":2,"cix":2,"bm":0,"ix":1,"mn":"ADBE Vector Group","hd":false}],"ip":0,"op":1,"st":-25,"bm":0},{"ddd":0,"ind":4,"ty":4,"nm":"“图层 5”轮廓","sr":1,"ks":{"o":{"a":0,"k":100,"ix":11},"r":{"a":0,"k":0,"ix":10},"p":{"a":1,"k":[{"i":{"x":0.667,"y":1},"o":{"x":0.333,"y":0},"t":15,"s":[60.719,49.186,0],"to":[-1.894,0,0],"ti":[1.894,0,0]},{"t":19,"s":[49.352,49.186,0]}],"ix":2},"a":{"a":0,"k":[17.136,5.017,0],"ix":1},"s":{"a":1,"k":[{"i":{"x":[0.667,0.667,0.667],"y":[1,1,1]},"o":{"x":[0.333,0.333,0.333],"y":[0,0,0]},"t":15,"s":[13.54,100,100]},{"t":19,"s":[88.156,100,100]}],"ix":6}},"ao":0,"shapes":[{"ty":"gr","it":[{"ind":0,"ty":"sh","ix":1,"ks":{"a":0,"k":{"i":[[2.632,0],[0,0],[0,2.632],[-2.633,0],[0,0],[0,-2.631]],"o":[[0,0],[-2.633,0],[0,-2.631],[0,0],[2.632,0],[0,2.632]],"v":[[12.12,4.766],[-12.12,4.766],[-16.887,-0.001],[-12.12,-4.766],[12.12,-4.766],[16.887,-0.001]],"c":true},"ix":2},"nm":"路径 1","mn":"ADBE Vector Shape - Group","hd":false},{"ty":"fl","c":{"a":0,"k":[0,0,0,1],"ix":4},"o":{"a":0,"k":100,"ix":5},"r":1,"bm":0,"nm":"填充 1","mn":"ADBE Vector Graphic - Fill","hd":false},{"ty":"tr","p":{"a":0,"k":[17.136,5.017],"ix":2},"a":{"a":0,"k":[0,0],"ix":1},"s":{"a":0,"k":[100,100],"ix":3},"r":{"a":0,"k":0,"ix":6},"o":{"a":0,"k":100,"ix":7},"sk":{"a":0,"k":0,"ix":4},"sa":{"a":0,"k":0,"ix":5},"nm":"变换"}],"nm":"组 1","np":2,"cix":2,"bm":0,"ix":1,"mn":"ADBE Vector Group","hd":false}],"ip":15,"op":50,"st":15,"bm":0},{"ddd":0,"ind":5,"ty":4,"nm":"“图层 4”轮廓 12","sr":1,"ks":{"o":{"a":0,"k":100,"ix":11},"r":{"a":0,"k":0,"ix":10},"p":{"a":0,"k":[64.553,50.726,0],"ix":2},"a":{"a":0,"k":[34.377,48.521,0],"ix":1},"s":{"a":0,"k":[100,100,100],"ix":6}},"ao":0,"shapes":[{"ty":"gr","it":[{"ind":0,"ty":"sh","ix":1,"ks":{"a":0,"k":{"i":[[0,0],[0,0]],"o":[[0,0],[0,0]],"v":[[24.499,-40.555],[24.499,-40.523]],"c":true},"ix":2},"nm":"路径 1","mn":"ADBE Vector Shape - Group","hd":false},{"ind":1,"ty":"sh","ix":2,"ks":{"a":0,"k":{"i":[[1.687,0],[0.726,0.396],[-1.261,2.312],[-18.557,-4.109],[-0.193,-0.006],[0.021,1.339],[0,0],[0,0],[4.562,-5.564],[0.02,-0.288],[2.635,0.185],[-0.186,2.623],[-14.61,18.07],[-10.2,-0.033],[0,0],[0.037,-4.213],[0,0],[6.593,-0.101],[0.855,0.181],[6.53,-11.972]],"o":[[-0.77,0],[-2.311,-1.261],[7.308,-13.4],[0.121,0.026],[1.328,-0.019],[0,0],[0,0],[-7.192,-0.062],[-12.692,15.697],[-0.191,2.623],[-2.625,-0.186],[0.093,-1.296],[6.414,-7.823],[0,0],[4.266,0.047],[0,0],[0.096,6.522],[-0.873,-0.013],[-9.991,-2.211],[-0.865,1.587]],"v":[[-14.309,48.271],[-16.588,47.688],[-18.49,41.221],[21.628,26.818],[22.117,26.859],[24.499,24.393],[24.499,-38.705],[9.009,-38.705],[-9.519,-30.027],[-24.432,14.613],[-29.527,19.025],[-33.941,13.936],[-16.911,-36.044],[9.039,-48.238],[26.406,-48.238],[34.031,-40.512],[34.031,24.322],[22.251,36.391],[19.615,36.135],[-10.12,45.785]],"c":true},"ix":2},"nm":"路径 2","mn":"ADBE Vector Shape - Group","hd":false},{"ty":"mm","mm":1,"nm":"合并路径 1","mn":"ADBE Vector Filter - Merge","hd":false},{"ty":"fl","c":{"a":0,"k":[0,0,0,1],"ix":4},"o":{"a":0,"k":100,"ix":5},"r":1,"bm":0,"nm":"填充 1","mn":"ADBE Vector Graphic - Fill","hd":false},{"ty":"tr","p":{"a":0,"k":[34.377,48.522],"ix":2},"a":{"a":0,"k":[0,0],"ix":1},"s":{"a":0,"k":[100,100],"ix":3},"r":{"a":0,"k":0,"ix":6},"o":{"a":0,"k":100,"ix":7},"sk":{"a":0,"k":0,"ix":4},"sa":{"a":0,"k":0,"ix":5},"nm":"变换"}],"nm":"组 1","np":4,"cix":2,"bm":0,"ix":1,"mn":"ADBE Vector Group","hd":false}],"ip":16,"op":50,"st":16,"bm":0},{"ddd":0,"ind":6,"ty":4,"nm":"“图层 4”轮廓 11","sr":1,"ks":{"o":{"a":0,"k":100,"ix":11},"r":{"a":0,"k":0,"ix":10},"p":{"a":0,"k":[64.553,50.726,0],"ix":2},"a":{"a":0,"k":[34.377,48.521,0],"ix":1},"s":{"a":0,"k":[100,100,100],"ix":6}},"ao":0,"shapes":[{"ty":"gr","it":[{"ind":0,"ty":"sh","ix":1,"ks":{"a":0,"k":{"i":[[0,0],[0,0]],"o":[[0,0],[0,0]],"v":[[24.499,-40.555],[24.499,-40.523]],"c":true},"ix":2},"nm":"路径 1","mn":"ADBE Vector Shape - Group","hd":false},{"ind":1,"ty":"sh","ix":2,"ks":{"a":0,"k":{"i":[[1.687,0],[0.726,0.396],[-1.261,2.312],[-18.557,-4.109],[-0.193,-0.006],[0.021,1.339],[0,0],[0,0],[4.562,-5.564],[1.831,-9.835],[-1.243,6.703],[-9.037,11.177],[-10.2,-0.033],[0,0],[0.037,-4.213],[0,0],[6.593,-0.101],[0.855,0.181],[6.53,-11.972]],"o":[[-0.77,0],[-2.311,-1.261],[7.308,-13.4],[0.121,0.026],[1.328,-0.019],[0,0],[0,0],[-7.192,-0.062],[-7.706,9.531],[-1.185,6.363],[2.016,-10.869],[6.414,-7.823],[0,0],[4.266,0.047],[0,0],[0.096,6.522],[-0.873,-0.013],[-9.991,-2.211],[-0.865,1.587]],"v":[[-14.309,48.271],[-16.588,47.688],[-18.49,41.221],[21.628,26.818],[22.117,26.859],[24.499,24.393],[24.499,-38.705],[9.009,-38.705],[-9.519,-30.027],[-22.895,3.646],[-32.302,1.977],[-16.911,-36.044],[9.039,-48.238],[26.406,-48.238],[34.031,-40.512],[34.031,24.322],[22.251,36.391],[19.615,36.135],[-10.12,45.785]],"c":true},"ix":2},"nm":"路径 2","mn":"ADBE Vector Shape - Group","hd":false},{"ty":"mm","mm":1,"nm":"合并路径 1","mn":"ADBE Vector Filter - Merge","hd":false},{"ty":"fl","c":{"a":0,"k":[0,0,0,1],"ix":4},"o":{"a":0,"k":100,"ix":5},"r":1,"bm":0,"nm":"填充 1","mn":"ADBE Vector Graphic - Fill","hd":false},{"ty":"tr","p":{"a":0,"k":[34.377,48.522],"ix":2},"a":{"a":0,"k":[0,0],"ix":1},"s":{"a":0,"k":[100,100],"ix":3},"r":{"a":0,"k":0,"ix":6},"o":{"a":0,"k":100,"ix":7},"sk":{"a":0,"k":0,"ix":4},"sa":{"a":0,"k":0,"ix":5},"nm":"变换"}],"nm":"组 1","np":4,"cix":2,"bm":0,"ix":1,"mn":"ADBE Vector Group","hd":false}],"ip":15,"op":16,"st":15,"bm":0},{"ddd":0,"ind":7,"ty":4,"nm":"“图层 4”轮廓 10","sr":1,"ks":{"o":{"a":0,"k":100,"ix":11},"r":{"a":0,"k":0,"ix":10},"p":{"a":0,"k":[64.553,50.726,0],"ix":2},"a":{"a":0,"k":[34.377,48.521,0],"ix":1},"s":{"a":0,"k":[100,100,100],"ix":6}},"ao":0,"shapes":[{"ty":"gr","it":[{"ind":0,"ty":"sh","ix":1,"ks":{"a":0,"k":{"i":[[0,0]],"o":[[0,0]],"v":[[95.324,50.295]],"c":false},"ix":2},"nm":"路径 1","mn":"ADBE Vector Shape - Group","hd":false},{"ty":"fl","c":{"a":0,"k":[0,0,0,1],"ix":4},"o":{"a":0,"k":100,"ix":5},"r":1,"bm":0,"nm":"填充 1","mn":"ADBE Vector Graphic - Fill","hd":false},{"ty":"tr","p":{"a":0,"k":[0,0],"ix":2},"a":{"a":0,"k":[0,0],"ix":1},"s":{"a":0,"k":[100,100],"ix":3},"r":{"a":0,"k":0,"ix":6},"o":{"a":0,"k":100,"ix":7},"sk":{"a":0,"k":0,"ix":4},"sa":{"a":0,"k":0,"ix":5},"nm":"变换"}],"nm":"形状 1","np":3,"cix":2,"bm":0,"ix":1,"mn":"ADBE Vector Group","hd":false},{"ty":"gr","it":[{"ind":0,"ty":"sh","ix":1,"ks":{"a":0,"k":{"i":[[0,0],[0,0]],"o":[[0,0],[0,0]],"v":[[24.499,-40.555],[24.499,-40.523]],"c":true},"ix":2},"nm":"路径 1","mn":"ADBE Vector Shape - Group","hd":false},{"ind":1,"ty":"sh","ix":2,"ks":{"a":0,"k":{"i":[[1.687,0],[0.726,0.396],[-1.261,2.312],[-18.557,-4.109],[-0.193,-0.006],[0.021,1.339],[0,0],[0,0],[4.562,-5.564],[2.076,-5.408],[-3.195,7.798],[-4.439,5.49],[-10.2,-0.033],[0,0],[0.037,-4.213],[0,0],[6.593,-0.101],[0.855,0.181],[6.53,-11.972]],"o":[[-0.77,0],[-2.311,-1.261],[7.308,-13.4],[0.121,0.026],[1.328,-0.019],[0,0],[0,0],[-7.192,-0.062],[-3.485,4.31],[-3.281,8.546],[2.681,-6.543],[6.414,-7.823],[0,0],[4.266,0.047],[0,0],[0.096,6.522],[-0.873,-0.013],[-9.991,-2.211],[-0.865,1.587]],"v":[[-14.309,48.271],[-16.588,47.688],[-18.49,41.221],[21.628,26.818],[22.117,26.859],[24.499,24.393],[24.499,-38.705],[9.009,-38.705],[-9.519,-30.027],[-17.772,-15.023],[-27.109,-17.274],[-16.911,-36.044],[9.039,-48.238],[26.406,-48.238],[34.031,-40.512],[34.031,24.322],[22.251,36.391],[19.615,36.135],[-10.12,45.785]],"c":true},"ix":2},"nm":"路径 2","mn":"ADBE Vector Shape - Group","hd":false},{"ty":"mm","mm":1,"nm":"合并路径 1","mn":"ADBE Vector Filter - Merge","hd":false},{"ty":"fl","c":{"a":0,"k":[0,0,0,1],"ix":4},"o":{"a":0,"k":100,"ix":5},"r":1,"bm":0,"nm":"填充 1","mn":"ADBE Vector Graphic - Fill","hd":false},{"ty":"tr","p":{"a":0,"k":[34.377,48.522],"ix":2},"a":{"a":0,"k":[0,0],"ix":1},"s":{"a":0,"k":[100,100],"ix":3},"r":{"a":0,"k":0,"ix":6},"o":{"a":0,"k":100,"ix":7},"sk":{"a":0,"k":0,"ix":4},"sa":{"a":0,"k":0,"ix":5},"nm":"变换"}],"nm":"组 1","np":4,"cix":2,"bm":0,"ix":2,"mn":"ADBE Vector Group","hd":false}],"ip":14,"op":15,"st":14,"bm":0},{"ddd":0,"ind":8,"ty":4,"nm":"“图层 4”轮廓 9","sr":1,"ks":{"o":{"a":0,"k":100,"ix":11},"r":{"a":0,"k":0,"ix":10},"p":{"a":0,"k":[64.553,50.726,0],"ix":2},"a":{"a":0,"k":[34.377,48.521,0],"ix":1},"s":{"a":0,"k":[100,100,100],"ix":6}},"ao":0,"shapes":[{"ty":"gr","it":[{"ind":0,"ty":"sh","ix":1,"ks":{"a":0,"k":{"i":[[0,0]],"o":[[0,0]],"v":[[81.824,43.795]],"c":false},"ix":2},"nm":"路径 1","mn":"ADBE Vector Shape - Group","hd":false},{"ty":"fl","c":{"a":0,"k":[0,0,0,1],"ix":4},"o":{"a":0,"k":100,"ix":5},"r":1,"bm":0,"nm":"填充 1","mn":"ADBE Vector Graphic - Fill","hd":false},{"ty":"tr","p":{"a":0,"k":[0,0],"ix":2},"a":{"a":0,"k":[0,0],"ix":1},"s":{"a":0,"k":[100,100],"ix":3},"r":{"a":0,"k":0,"ix":6},"o":{"a":0,"k":100,"ix":7},"sk":{"a":0,"k":0,"ix":4},"sa":{"a":0,"k":0,"ix":5},"nm":"变换"}],"nm":"形状 1","np":3,"cix":2,"bm":0,"ix":1,"mn":"ADBE Vector Group","hd":false},{"ty":"gr","it":[{"ind":0,"ty":"sh","ix":1,"ks":{"a":0,"k":{"i":[[0,0],[0,0]],"o":[[0,0],[0,0]],"v":[[24.499,-40.555],[24.499,-40.523]],"c":true},"ix":2},"nm":"路径 1","mn":"ADBE Vector Shape - Group","hd":false},{"ind":1,"ty":"sh","ix":2,"ks":{"a":0,"k":{"i":[[1.687,0],[0.726,0.396],[-1.261,2.312],[-18.557,-4.109],[-0.193,-0.006],[0.021,1.339],[0,0],[0,0],[4.562,-5.564],[-3.642,8.568],[-10.2,-0.033],[0,0],[0.037,-4.213],[0,0],[6.593,-0.101],[0.855,0.181],[6.53,-11.972]],"o":[[-0.77,0],[-2.311,-1.261],[7.308,-13.4],[0.121,0.026],[1.328,-0.019],[0,0],[0,0],[-7.192,-0.062],[-2.785,3.55],[6.414,-7.823],[0,0],[4.266,0.047],[0,0],[0.096,6.522],[-0.873,-0.013],[-9.991,-2.211],[-0.865,1.587]],"v":[[-14.309,48.271],[-16.588,47.688],[-18.49,41.221],[21.628,26.818],[22.117,26.859],[24.499,24.393],[24.499,-38.705],[9.009,-38.705],[-9.519,-30.027],[-16.911,-36.044],[9.039,-48.238],[26.406,-48.238],[34.031,-40.512],[34.031,24.322],[22.251,36.391],[19.615,36.135],[-10.12,45.785]],"c":true},"ix":2},"nm":"路径 2","mn":"ADBE Vector Shape - Group","hd":false},{"ty":"mm","mm":1,"nm":"合并路径 1","mn":"ADBE Vector Filter - Merge","hd":false},{"ty":"fl","c":{"a":0,"k":[0,0,0,1],"ix":4},"o":{"a":0,"k":100,"ix":5},"r":1,"bm":0,"nm":"填充 1","mn":"ADBE Vector Graphic - Fill","hd":false},{"ty":"tr","p":{"a":0,"k":[34.377,48.522],"ix":2},"a":{"a":0,"k":[0,0],"ix":1},"s":{"a":0,"k":[100,100],"ix":3},"r":{"a":0,"k":0,"ix":6},"o":{"a":0,"k":100,"ix":7},"sk":{"a":0,"k":0,"ix":4},"sa":{"a":0,"k":0,"ix":5},"nm":"变换"}],"nm":"组 1","np":4,"cix":2,"bm":0,"ix":2,"mn":"ADBE Vector Group","hd":false}],"ip":13,"op":14,"st":13,"bm":0},{"ddd":0,"ind":9,"ty":4,"nm":"“图层 4”轮廓 8","sr":1,"ks":{"o":{"a":0,"k":100,"ix":11},"r":{"a":0,"k":0,"ix":10},"p":{"a":0,"k":[64.553,50.726,0],"ix":2},"a":{"a":0,"k":[34.377,48.521,0],"ix":1},"s":{"a":0,"k":[100,100,100],"ix":6}},"ao":0,"shapes":[{"ty":"gr","it":[{"ind":0,"ty":"sh","ix":1,"ks":{"a":0,"k":{"i":[[0,0],[0,0]],"o":[[0,0],[0,0]],"v":[[24.499,-40.555],[24.499,-40.523]],"c":true},"ix":2},"nm":"路径 1","mn":"ADBE Vector Shape - Group","hd":false},{"ind":1,"ty":"sh","ix":2,"ks":{"a":0,"k":{"i":[[1.687,0],[0.726,0.396],[-1.261,2.312],[-18.557,-4.109],[-0.193,-0.006],[0.021,1.339],[0,0],[0,0],[-10.2,-0.033],[0,0],[0.037,-4.213],[0,0],[6.593,-0.101],[0.855,0.181],[6.53,-11.972]],"o":[[-0.77,0],[-2.311,-1.261],[7.308,-13.4],[0.121,0.026],[1.328,-0.019],[0,0],[0,0],[-7.192,-0.062],[0,0],[4.266,0.047],[0,0],[0.096,6.522],[-0.873,-0.013],[-9.991,-2.211],[-0.865,1.587]],"v":[[-14.309,48.271],[-16.588,47.688],[-18.49,41.221],[21.628,26.818],[22.117,26.859],[24.499,24.393],[24.499,-38.705],[9.009,-38.705],[9.039,-48.238],[26.406,-48.238],[34.031,-40.512],[34.031,24.322],[22.251,36.391],[19.615,36.135],[-10.12,45.785]],"c":true},"ix":2},"nm":"路径 2","mn":"ADBE Vector Shape - Group","hd":false},{"ty":"mm","mm":1,"nm":"合并路径 1","mn":"ADBE Vector Filter - Merge","hd":false},{"ty":"fl","c":{"a":0,"k":[0,0,0,1],"ix":4},"o":{"a":0,"k":100,"ix":5},"r":1,"bm":0,"nm":"填充 1","mn":"ADBE Vector Graphic - Fill","hd":false},{"ty":"tr","p":{"a":0,"k":[34.377,48.522],"ix":2},"a":{"a":0,"k":[0,0],"ix":1},"s":{"a":0,"k":[100,100],"ix":3},"r":{"a":0,"k":0,"ix":6},"o":{"a":0,"k":100,"ix":7},"sk":{"a":0,"k":0,"ix":4},"sa":{"a":0,"k":0,"ix":5},"nm":"变换"}],"nm":"组 1","np":4,"cix":2,"bm":0,"ix":1,"mn":"ADBE Vector Group","hd":false}],"ip":12,"op":13,"st":12,"bm":0},{"ddd":0,"ind":10,"ty":4,"nm":"“图层 4”轮廓 7","sr":1,"ks":{"o":{"a":0,"k":100,"ix":11},"r":{"a":0,"k":0,"ix":10},"p":{"a":0,"k":[64.553,50.726,0],"ix":2},"a":{"a":0,"k":[34.377,48.521,0],"ix":1},"s":{"a":0,"k":[100,100,100],"ix":6}},"ao":0,"shapes":[{"ty":"gr","it":[{"ind":0,"ty":"sh","ix":1,"ks":{"a":0,"k":{"i":[[0,0],[0,0]],"o":[[0,0],[0,0]],"v":[[24.499,-40.555],[24.499,-40.523]],"c":true},"ix":2},"nm":"路径 1","mn":"ADBE Vector Shape - Group","hd":false},{"ind":1,"ty":"sh","ix":2,"ks":{"a":0,"k":{"i":[[1.687,0],[0.726,0.396],[-1.261,2.312],[-18.557,-4.109],[-0.193,-0.006],[0.021,1.339],[0,0],[0,0],[0.037,-4.213],[0,0],[6.593,-0.101],[0.855,0.181],[6.53,-11.972]],"o":[[-0.77,0],[-2.311,-1.261],[7.308,-13.4],[0.121,0.026],[1.328,-0.019],[0,0],[0,0],[4.266,0.047],[0,0],[0.096,6.522],[-0.873,-0.013],[-9.991,-2.211],[-0.865,1.587]],"v":[[-14.309,48.271],[-16.588,47.688],[-18.49,41.221],[21.628,26.818],[22.117,26.859],[24.499,24.393],[24.499,-38.705],[26.406,-48.238],[34.031,-40.512],[34.031,24.322],[22.251,36.391],[19.615,36.135],[-10.12,45.785]],"c":true},"ix":2},"nm":"路径 2","mn":"ADBE Vector Shape - Group","hd":false},{"ty":"mm","mm":1,"nm":"合并路径 1","mn":"ADBE Vector Filter - Merge","hd":false},{"ty":"fl","c":{"a":0,"k":[0,0,0,1],"ix":4},"o":{"a":0,"k":100,"ix":5},"r":1,"bm":0,"nm":"填充 1","mn":"ADBE Vector Graphic - Fill","hd":false},{"ty":"tr","p":{"a":0,"k":[34.377,48.522],"ix":2},"a":{"a":0,"k":[0,0],"ix":1},"s":{"a":0,"k":[100,100],"ix":3},"r":{"a":0,"k":0,"ix":6},"o":{"a":0,"k":100,"ix":7},"sk":{"a":0,"k":0,"ix":4},"sa":{"a":0,"k":0,"ix":5},"nm":"变换"}],"nm":"组 1","np":4,"cix":2,"bm":0,"ix":1,"mn":"ADBE Vector Group","hd":false}],"ip":11,"op":12,"st":11,"bm":0},{"ddd":0,"ind":11,"ty":4,"nm":"“图层 4”轮廓 6","sr":1,"ks":{"o":{"a":0,"k":100,"ix":11},"r":{"a":0,"k":0,"ix":10},"p":{"a":0,"k":[64.553,50.726,0],"ix":2},"a":{"a":0,"k":[34.377,48.521,0],"ix":1},"s":{"a":0,"k":[100,100,100],"ix":6}},"ao":0,"shapes":[{"ty":"gr","it":[{"ind":0,"ty":"sh","ix":1,"ks":{"a":0,"k":{"i":[[0,0],[0,0]],"o":[[0,0],[0,0]],"v":[[24.499,-40.555],[24.499,-40.523]],"c":true},"ix":2},"nm":"路径 1","mn":"ADBE Vector Shape - Group","hd":false},{"ind":1,"ty":"sh","ix":2,"ks":{"a":0,"k":{"i":[[1.687,0],[0.726,0.396],[-1.261,2.312],[-18.557,-4.109],[-0.193,-0.006],[0.021,1.339],[0,0],[0,0],[0,0],[6.593,-0.101],[0.855,0.181],[6.53,-11.972]],"o":[[-0.77,0],[-2.311,-1.261],[7.308,-13.4],[0.121,0.026],[1.328,-0.019],[0,0],[0,0],[0,0],[0.096,6.522],[-0.873,-0.013],[-9.991,-2.211],[-0.865,1.587]],"v":[[-14.309,48.271],[-16.588,47.688],[-18.49,41.221],[21.628,26.818],[22.117,26.859],[24.499,24.393],[24.499,-22.226],[34.031,-21.976],[34.031,24.322],[22.251,36.391],[19.615,36.135],[-10.12,45.785]],"c":true},"ix":2},"nm":"路径 2","mn":"ADBE Vector Shape - Group","hd":false},{"ty":"mm","mm":1,"nm":"合并路径 1","mn":"ADBE Vector Filter - Merge","hd":false},{"ty":"fl","c":{"a":0,"k":[0,0,0,1],"ix":4},"o":{"a":0,"k":100,"ix":5},"r":1,"bm":0,"nm":"填充 1","mn":"ADBE Vector Graphic - Fill","hd":false},{"ty":"tr","p":{"a":0,"k":[34.377,48.522],"ix":2},"a":{"a":0,"k":[0,0],"ix":1},"s":{"a":0,"k":[100,100],"ix":3},"r":{"a":0,"k":0,"ix":6},"o":{"a":0,"k":100,"ix":7},"sk":{"a":0,"k":0,"ix":4},"sa":{"a":0,"k":0,"ix":5},"nm":"变换"}],"nm":"组 1","np":4,"cix":2,"bm":0,"ix":1,"mn":"ADBE Vector Group","hd":false}],"ip":10,"op":11,"st":10,"bm":0},{"ddd":0,"ind":12,"ty":4,"nm":"“图层 4”轮廓 5","sr":1,"ks":{"o":{"a":0,"k":100,"ix":11},"r":{"a":0,"k":0,"ix":10},"p":{"a":0,"k":[64.553,50.726,0],"ix":2},"a":{"a":0,"k":[34.377,48.521,0],"ix":1},"s":{"a":0,"k":[100,100,100],"ix":6}},"ao":0,"shapes":[{"ty":"gr","it":[{"ind":0,"ty":"sh","ix":1,"ks":{"a":0,"k":{"i":[[0,0],[0,0]],"o":[[0,0],[0,0]],"v":[[24.499,-40.555],[24.499,-40.523]],"c":true},"ix":2},"nm":"路径 1","mn":"ADBE Vector Shape - Group","hd":false},{"ind":1,"ty":"sh","ix":2,"ks":{"a":0,"k":{"i":[[1.687,0],[0.726,0.396],[-1.261,2.312],[-18.557,-4.109],[-0.193,-0.006],[0.021,1.339],[0,0],[0,0],[0,0],[6.593,-0.101],[0.855,0.181],[6.53,-11.972]],"o":[[-0.77,0],[-2.311,-1.261],[7.308,-13.4],[0.121,0.026],[1.328,-0.019],[0,0],[0,0],[0,0],[0.096,6.522],[-0.873,-0.013],[-9.991,-2.211],[-0.865,1.587]],"v":[[-14.309,48.271],[-16.588,47.688],[-18.49,41.221],[21.628,26.818],[22.117,26.859],[24.499,24.393],[24.499,-4.976],[34.031,-4.976],[34.031,24.322],[22.251,36.391],[19.615,36.135],[-10.12,45.785]],"c":true},"ix":2},"nm":"路径 2","mn":"ADBE Vector Shape - Group","hd":false},{"ty":"mm","mm":1,"nm":"合并路径 1","mn":"ADBE Vector Filter - Merge","hd":false},{"ty":"fl","c":{"a":0,"k":[0,0,0,1],"ix":4},"o":{"a":0,"k":100,"ix":5},"r":1,"bm":0,"nm":"填充 1","mn":"ADBE Vector Graphic - Fill","hd":false},{"ty":"tr","p":{"a":0,"k":[34.377,48.522],"ix":2},"a":{"a":0,"k":[0,0],"ix":1},"s":{"a":0,"k":[100,100],"ix":3},"r":{"a":0,"k":0,"ix":6},"o":{"a":0,"k":100,"ix":7},"sk":{"a":0,"k":0,"ix":4},"sa":{"a":0,"k":0,"ix":5},"nm":"变换"}],"nm":"组 1","np":4,"cix":2,"bm":0,"ix":1,"mn":"ADBE Vector Group","hd":false}],"ip":9,"op":10,"st":9,"bm":0},{"ddd":0,"ind":13,"ty":4,"nm":"“图层 4”轮廓 4","sr":1,"ks":{"o":{"a":0,"k":100,"ix":11},"r":{"a":0,"k":0,"ix":10},"p":{"a":0,"k":[64.553,50.726,0],"ix":2},"a":{"a":0,"k":[34.377,48.521,0],"ix":1},"s":{"a":0,"k":[100,100,100],"ix":6}},"ao":0,"shapes":[{"ty":"gr","it":[{"ind":0,"ty":"sh","ix":1,"ks":{"a":0,"k":{"i":[[0,0],[0,0]],"o":[[0,0],[0,0]],"v":[[24.499,-40.555],[24.499,-40.523]],"c":true},"ix":2},"nm":"路径 1","mn":"ADBE Vector Shape - Group","hd":false},{"ind":1,"ty":"sh","ix":2,"ks":{"a":0,"k":{"i":[[1.687,0],[0.726,0.396],[-1.261,2.312],[-18.557,-4.109],[-0.193,-0.006],[0.021,1.339],[0,0],[0,0],[0,0],[6.593,-0.101],[0.855,0.181],[6.53,-11.972]],"o":[[-0.77,0],[-2.311,-1.261],[7.308,-13.4],[0.121,0.026],[1.328,-0.019],[0,0],[0,0],[0,0],[0.096,6.522],[-0.873,-0.013],[-9.991,-2.211],[-0.865,1.587]],"v":[[-14.309,48.271],[-16.588,47.688],[-18.49,41.222],[21.628,26.818],[22.117,26.859],[24.499,24.393],[24.499,9.774],[34.031,9.774],[34.031,24.322],[22.251,36.391],[19.615,36.135],[-10.12,45.785]],"c":true},"ix":2},"nm":"路径 2","mn":"ADBE Vector Shape - Group","hd":false},{"ty":"mm","mm":1,"nm":"合并路径 1","mn":"ADBE Vector Filter - Merge","hd":false},{"ty":"fl","c":{"a":0,"k":[0,0,0,1],"ix":4},"o":{"a":0,"k":100,"ix":5},"r":1,"bm":0,"nm":"填充 1","mn":"ADBE Vector Graphic - Fill","hd":false},{"ty":"tr","p":{"a":0,"k":[34.377,48.522],"ix":2},"a":{"a":0,"k":[0,0],"ix":1},"s":{"a":0,"k":[100,100],"ix":3},"r":{"a":0,"k":0,"ix":6},"o":{"a":0,"k":100,"ix":7},"sk":{"a":0,"k":0,"ix":4},"sa":{"a":0,"k":0,"ix":5},"nm":"变换"}],"nm":"组 1","np":4,"cix":2,"bm":0,"ix":1,"mn":"ADBE Vector Group","hd":false}],"ip":8,"op":9,"st":8,"bm":0},{"ddd":0,"ind":14,"ty":4,"nm":"“图层 4”轮廓 3","sr":1,"ks":{"o":{"a":0,"k":100,"ix":11},"r":{"a":0,"k":0,"ix":10},"p":{"a":0,"k":[64.553,50.726,0],"ix":2},"a":{"a":0,"k":[34.377,48.521,0],"ix":1},"s":{"a":0,"k":[100,100,100],"ix":6}},"ao":0,"shapes":[{"ty":"gr","it":[{"ind":0,"ty":"sh","ix":1,"ks":{"a":0,"k":{"i":[[0,0],[0,0]],"o":[[0,0],[0,0]],"v":[[24.499,-40.555],[24.499,-40.523]],"c":true},"ix":2},"nm":"路径 1","mn":"ADBE Vector Shape - Group","hd":false},{"ind":1,"ty":"sh","ix":2,"ks":{"a":0,"k":{"i":[[1.687,0],[0.726,0.396],[-1.261,2.312],[-18.557,-4.109],[-0.193,-0.006],[0.021,1.339],[0,0],[6.593,-0.101],[0.855,0.181],[6.53,-11.972]],"o":[[-0.77,0],[-2.311,-1.261],[7.308,-13.4],[0.121,0.026],[1.328,-0.019],[0,0],[0.096,6.522],[-0.873,-0.013],[-9.991,-2.211],[-0.865,1.587]],"v":[[-14.309,48.271],[-16.588,47.688],[-18.49,41.221],[21.628,26.818],[22.117,26.859],[24.499,24.393],[34.031,24.322],[22.251,36.391],[19.615,36.135],[-10.12,45.785]],"c":true},"ix":2},"nm":"路径 2","mn":"ADBE Vector Shape - Group","hd":false},{"ty":"mm","mm":1,"nm":"合并路径 1","mn":"ADBE Vector Filter - Merge","hd":false},{"ty":"fl","c":{"a":0,"k":[0,0,0,1],"ix":4},"o":{"a":0,"k":100,"ix":5},"r":1,"bm":0,"nm":"填充 1","mn":"ADBE Vector Graphic - Fill","hd":false},{"ty":"tr","p":{"a":0,"k":[34.377,48.522],"ix":2},"a":{"a":0,"k":[0,0],"ix":1},"s":{"a":0,"k":[100,100],"ix":3},"r":{"a":0,"k":0,"ix":6},"o":{"a":0,"k":100,"ix":7},"sk":{"a":0,"k":0,"ix":4},"sa":{"a":0,"k":0,"ix":5},"nm":"变换"}],"nm":"组 1","np":4,"cix":2,"bm":0,"ix":1,"mn":"ADBE Vector Group","hd":false}],"ip":7,"op":8,"st":7,"bm":0},{"ddd":0,"ind":15,"ty":4,"nm":"“图层 4”轮廓 2","sr":1,"ks":{"o":{"a":0,"k":100,"ix":11},"r":{"a":0,"k":0,"ix":10},"p":{"a":0,"k":[64.553,50.726,0],"ix":2},"a":{"a":0,"k":[34.377,48.521,0],"ix":1},"s":{"a":0,"k":[100,100,100],"ix":6}},"ao":0,"shapes":[{"ty":"gr","it":[{"ind":0,"ty":"sh","ix":1,"ks":{"a":0,"k":{"i":[[0,0],[0,0]],"o":[[0,0],[0,0]],"v":[[24.499,-40.555],[24.499,-40.523]],"c":true},"ix":2},"nm":"路径 1","mn":"ADBE Vector Shape - Group","hd":false},{"ind":1,"ty":"sh","ix":2,"ks":{"a":0,"k":{"i":[[1.687,0],[0.726,0.396],[-1.261,2.312],[-13.229,-0.273],[2.915,0.105],[4.8,-8.8]],"o":[[-0.77,0],[-2.311,-1.261],[5.8,-10.635],[3.439,0.071],[-8.088,-0.292],[-0.865,1.587]],"v":[[-14.309,48.271],[-16.588,47.688],[-18.49,41.221],[10.714,25.445],[11.179,35.006],[-10.12,45.785]],"c":true},"ix":2},"nm":"路径 2","mn":"ADBE Vector Shape - Group","hd":false},{"ty":"mm","mm":1,"nm":"合并路径 1","mn":"ADBE Vector Filter - Merge","hd":false},{"ty":"fl","c":{"a":0,"k":[0,0,0,1],"ix":4},"o":{"a":0,"k":100,"ix":5},"r":1,"bm":0,"nm":"填充 1","mn":"ADBE Vector Graphic - Fill","hd":false},{"ty":"tr","p":{"a":0,"k":[34.377,48.522],"ix":2},"a":{"a":0,"k":[0,0],"ix":1},"s":{"a":0,"k":[100,100],"ix":3},"r":{"a":0,"k":0,"ix":6},"o":{"a":0,"k":100,"ix":7},"sk":{"a":0,"k":0,"ix":4},"sa":{"a":0,"k":0,"ix":5},"nm":"变换"}],"nm":"组 1","np":4,"cix":2,"bm":0,"ix":1,"mn":"ADBE Vector Group","hd":false}],"ip":6,"op":7,"st":6,"bm":0},{"ddd":0,"ind":16,"ty":4,"nm":"“图层 4”轮廓","sr":1,"ks":{"o":{"a":0,"k":100,"ix":11},"r":{"a":0,"k":0,"ix":10},"p":{"a":0,"k":[64.553,50.726,0],"ix":2},"a":{"a":0,"k":[34.377,48.521,0],"ix":1},"s":{"a":0,"k":[100,100,100],"ix":6}},"ao":0,"shapes":[{"ty":"gr","it":[{"ind":0,"ty":"sh","ix":1,"ks":{"a":0,"k":{"i":[[0,0],[0,0]],"o":[[0,0],[0,0]],"v":[[24.499,-40.555],[24.499,-40.523]],"c":true},"ix":2},"nm":"路径 1","mn":"ADBE Vector Shape - Group","hd":false},{"ind":1,"ty":"sh","ix":2,"ks":{"a":0,"k":{"i":[[1.687,0],[0.726,0.396],[-1.261,2.312],[-2.027,2.026],[7.068,-6.719],[1.122,-2.058]],"o":[[-0.77,0],[-2.311,-1.261],[1.48,-2.713],[7.985,-7.979],[-1.467,1.394],[-0.865,1.587]],"v":[[-14.309,48.271],[-16.588,47.688],[-18.49,41.221],[-13.218,34.109],[-6.212,40.633],[-10.12,45.785]],"c":true},"ix":2},"nm":"路径 2","mn":"ADBE Vector Shape - Group","hd":false},{"ty":"mm","mm":1,"nm":"合并路径 1","mn":"ADBE Vector Filter - Merge","hd":false},{"ty":"fl","c":{"a":0,"k":[0,0,0,1],"ix":4},"o":{"a":0,"k":100,"ix":5},"r":1,"bm":0,"nm":"填充 1","mn":"ADBE Vector Graphic - Fill","hd":false},{"ty":"tr","p":{"a":0,"k":[34.377,48.522],"ix":2},"a":{"a":0,"k":[0,0],"ix":1},"s":{"a":0,"k":[100,100],"ix":3},"r":{"a":0,"k":0,"ix":6},"o":{"a":0,"k":100,"ix":7},"sk":{"a":0,"k":0,"ix":4},"sa":{"a":0,"k":0,"ix":5},"nm":"变换"}],"nm":"组 1","np":4,"cix":2,"bm":0,"ix":1,"mn":"ADBE Vector Group","hd":false}],"ip":5,"op":6,"st":5,"bm":0},{"ddd":0,"ind":17,"ty":4,"nm":"“图层 6”轮廓 12","sr":1,"ks":{"o":{"a":0,"k":100,"ix":11},"r":{"a":0,"k":0,"ix":10},"p":{"a":0,"k":[35.727,50.728,0],"ix":2},"a":{"a":0,"k":[33.976,48.522,0],"ix":1},"s":{"a":0,"k":[100,100,100],"ix":6}},"ao":0,"shapes":[{"ty":"gr","it":[{"ind":0,"ty":"sh","ix":1,"ks":{"a":0,"k":{"i":[[0,0],[0,0]],"o":[[0,0],[0,0]],"v":[[-24.12,-40.634],[-24.12,-40.589]],"c":true},"ix":2},"nm":"路径 1","mn":"ADBE Vector Shape - Group","hd":false},{"ind":1,"ty":"sh","ix":2,"ks":{"a":0,"k":{"i":[[0.761,0],[0.859,1.6],[9.767,-2.198],[0.889,0.03],[2.194,2.298],[-0.076,3.176],[0,0],[-4.205,0.05],[0,0],[-6.114,-6.842],[-0.095,-1.368],[2.623,-0.186],[0.188,2.624],[13.447,15.384],[6.348,0],[0.075,-0.001],[0,0],[0,0],[-0.254,-0.265],[-0.852,-0.019],[-0.175,0.036],[-7.223,-13.424],[2.317,-1.247]],"o":[[-1.699,0],[-6.43,-11.943],[-0.961,0.197],[-3.186,-0.076],[-2.192,-2.3],[0,0],[-0.049,-4.151],[0,0],[9.232,-0.035],[15.604,17.849],[0.184,2.625],[-2.693,0.201],[-0.021,-0.303],[-4.199,-4.699],[-0.075,0],[0,0],[0,0],[-0.021,0.962],[0.251,0.264],[0.179,-0.002],[18.266,-4.101],[1.247,2.318],[-0.717,0.387]],"v":[[14.112,48.272],[9.911,45.763],[-19.286,36.124],[-22.03,36.382],[-30.366,32.702],[-33.65,24.211],[-33.652,-40.574],[-26.117,-48.237],[-8.609,-48.237],[15.406,-37.616],[33.542,13.937],[29.125,19.025],[24.033,14.607],[8.264,-31.304],[-8.334,-38.706],[-8.56,-38.705],[-24.12,-38.705],[-24.12,24.324],[-23.468,26.121],[-21.816,26.851],[-21.285,26.804],[18.303,41.246],[16.365,47.702]],"c":true},"ix":2},"nm":"路径 2","mn":"ADBE Vector Shape - Group","hd":false},{"ty":"mm","mm":1,"nm":"合并路径 1","mn":"ADBE Vector Filter - Merge","hd":false},{"ty":"fl","c":{"a":0,"k":[0,0,0,1],"ix":4},"o":{"a":0,"k":100,"ix":5},"r":1,"bm":0,"nm":"填充 1","mn":"ADBE Vector Graphic - Fill","hd":false},{"ty":"tr","p":{"a":0,"k":[33.976,48.522],"ix":2},"a":{"a":0,"k":[0,0],"ix":1},"s":{"a":0,"k":[100,100],"ix":3},"r":{"a":0,"k":0,"ix":6},"o":{"a":0,"k":100,"ix":7},"sk":{"a":0,"k":0,"ix":4},"sa":{"a":0,"k":0,"ix":5},"nm":"变换"}],"nm":"组 1","np":4,"cix":2,"bm":0,"ix":1,"mn":"ADBE Vector Group","hd":false}],"ip":16,"op":50,"st":16,"bm":0},{"ddd":0,"ind":18,"ty":4,"nm":"“图层 6”轮廓 11","sr":1,"ks":{"o":{"a":0,"k":100,"ix":11},"r":{"a":0,"k":0,"ix":10},"p":{"a":0,"k":[35.727,50.728,0],"ix":2},"a":{"a":0,"k":[33.976,48.522,0],"ix":1},"s":{"a":0,"k":[100,100,100],"ix":6}},"ao":0,"shapes":[{"ty":"gr","it":[{"ind":0,"ty":"sh","ix":1,"ks":{"a":0,"k":{"i":[[0,0],[0,0]],"o":[[0,0],[0,0]],"v":[[-24.12,-40.634],[-24.12,-40.589]],"c":true},"ix":2},"nm":"路径 1","mn":"ADBE Vector Shape - Group","hd":false},{"ind":1,"ty":"sh","ix":2,"ks":{"a":0,"k":{"i":[[0.761,0],[0.859,1.6],[9.767,-2.198],[0.889,0.03],[2.194,2.298],[-0.076,3.176],[0,0],[-4.205,0.05],[0,0],[-6.114,-6.842],[-1.937,-11.331],[0.878,5.244],[8.884,10.164],[6.348,0],[0.075,-0.001],[0,0],[0,0],[-0.254,-0.265],[-0.852,-0.019],[-0.175,0.036],[-7.223,-13.424],[2.317,-1.247]],"o":[[-1.699,0],[-6.43,-11.943],[-0.961,0.197],[-3.186,-0.076],[-2.192,-2.3],[0,0],[-0.049,-4.151],[0,0],[9.232,-0.035],[10.308,11.791],[0.995,5.822],[-1.711,-10.211],[-4.199,-4.699],[-0.075,0],[0,0],[0,0],[-0.021,0.962],[0.251,0.264],[0.179,-0.002],[18.266,-4.101],[1.247,2.318],[-0.717,0.387]],"v":[[14.112,48.272],[9.911,45.763],[-19.286,36.124],[-22.03,36.382],[-30.366,32.702],[-33.65,24.211],[-33.652,-40.574],[-26.117,-48.237],[-8.609,-48.237],[15.406,-37.616],[32.212,3.618],[22.878,5.713],[8.264,-31.304],[-8.334,-38.706],[-8.56,-38.705],[-24.12,-38.705],[-24.12,24.324],[-23.468,26.121],[-21.816,26.851],[-21.285,26.804],[18.303,41.246],[16.365,47.702]],"c":true},"ix":2},"nm":"路径 2","mn":"ADBE Vector Shape - Group","hd":false},{"ty":"mm","mm":1,"nm":"合并路径 1","mn":"ADBE Vector Filter - Merge","hd":false},{"ty":"fl","c":{"a":0,"k":[0,0,0,1],"ix":4},"o":{"a":0,"k":100,"ix":5},"r":1,"bm":0,"nm":"填充 1","mn":"ADBE Vector Graphic - Fill","hd":false},{"ty":"tr","p":{"a":0,"k":[33.976,48.522],"ix":2},"a":{"a":0,"k":[0,0],"ix":1},"s":{"a":0,"k":[100,100],"ix":3},"r":{"a":0,"k":0,"ix":6},"o":{"a":0,"k":100,"ix":7},"sk":{"a":0,"k":0,"ix":4},"sa":{"a":0,"k":0,"ix":5},"nm":"变换"}],"nm":"组 1","np":4,"cix":2,"bm":0,"ix":1,"mn":"ADBE Vector Group","hd":false}],"ip":15,"op":16,"st":15,"bm":0},{"ddd":0,"ind":19,"ty":4,"nm":"“图层 6”轮廓 10","sr":1,"ks":{"o":{"a":0,"k":100,"ix":11},"r":{"a":0,"k":0,"ix":10},"p":{"a":0,"k":[35.727,50.728,0],"ix":2},"a":{"a":0,"k":[33.976,48.522,0],"ix":1},"s":{"a":0,"k":[100,100,100],"ix":6}},"ao":0,"shapes":[{"ty":"gr","it":[{"ind":0,"ty":"sh","ix":1,"ks":{"a":0,"k":{"i":[[0,0]],"o":[[0,0]],"v":[[122.749,41.544]],"c":false},"ix":2},"nm":"路径 1","mn":"ADBE Vector Shape - Group","hd":false},{"ty":"fl","c":{"a":0,"k":[0,0,0,1],"ix":4},"o":{"a":0,"k":100,"ix":5},"r":1,"bm":0,"nm":"填充 1","mn":"ADBE Vector Graphic - Fill","hd":false},{"ty":"tr","p":{"a":0,"k":[0,0],"ix":2},"a":{"a":0,"k":[0,0],"ix":1},"s":{"a":0,"k":[100,100],"ix":3},"r":{"a":0,"k":0,"ix":6},"o":{"a":0,"k":100,"ix":7},"sk":{"a":0,"k":0,"ix":4},"sa":{"a":0,"k":0,"ix":5},"nm":"变换"}],"nm":"形状 1","np":3,"cix":2,"bm":0,"ix":1,"mn":"ADBE Vector Group","hd":false},{"ty":"gr","it":[{"ind":0,"ty":"sh","ix":1,"ks":{"a":0,"k":{"i":[[0,0],[0,0]],"o":[[0,0],[0,0]],"v":[[-24.12,-40.634],[-24.12,-40.589]],"c":true},"ix":2},"nm":"路径 1","mn":"ADBE Vector Shape - Group","hd":false},{"ind":1,"ty":"sh","ix":2,"ks":{"a":0,"k":{"i":[[0.761,0],[0.859,1.6],[9.767,-2.198],[0.889,0.03],[2.194,2.298],[-0.076,3.176],[0,0],[-4.205,0.05],[0,0],[-6.114,-6.842],[-3.18,-8.167],[0.854,3.133],[4.708,5.386],[6.348,0],[0.075,-0.001],[0,0],[0,0],[-0.254,-0.265],[-0.852,-0.019],[-0.175,0.036],[-7.223,-13.424],[2.317,-1.247]],"o":[[-1.699,0],[-6.43,-11.943],[-0.961,0.197],[-3.186,-0.076],[-2.192,-2.3],[0,0],[-0.049,-4.151],[0,0],[9.232,-0.035],[5.822,6.659],[1.838,4.721],[-1.968,-7.22],[-4.199,-4.699],[-0.075,0],[0,0],[0,0],[-0.021,0.962],[0.251,0.264],[0.179,-0.002],[18.266,-4.101],[1.247,2.318],[-0.717,0.387]],"v":[[14.112,48.272],[9.911,45.763],[-19.286,36.124],[-22.03,36.382],[-30.366,32.702],[-33.65,24.211],[-33.652,-40.574],[-26.117,-48.237],[-8.609,-48.237],[15.406,-37.616],[27.935,-13.949],[18.669,-11.61],[8.264,-31.304],[-8.334,-38.706],[-8.56,-38.705],[-24.12,-38.705],[-24.12,24.324],[-23.468,26.121],[-21.816,26.851],[-21.285,26.804],[18.303,41.246],[16.365,47.702]],"c":true},"ix":2},"nm":"路径 2","mn":"ADBE Vector Shape - Group","hd":false},{"ty":"mm","mm":1,"nm":"合并路径 1","mn":"ADBE Vector Filter - Merge","hd":false},{"ty":"fl","c":{"a":0,"k":[0,0,0,1],"ix":4},"o":{"a":0,"k":100,"ix":5},"r":1,"bm":0,"nm":"填充 1","mn":"ADBE Vector Graphic - Fill","hd":false},{"ty":"tr","p":{"a":0,"k":[33.976,48.522],"ix":2},"a":{"a":0,"k":[0,0],"ix":1},"s":{"a":0,"k":[100,100],"ix":3},"r":{"a":0,"k":0,"ix":6},"o":{"a":0,"k":100,"ix":7},"sk":{"a":0,"k":0,"ix":4},"sa":{"a":0,"k":0,"ix":5},"nm":"变换"}],"nm":"组 1","np":4,"cix":2,"bm":0,"ix":2,"mn":"ADBE Vector Group","hd":false}],"ip":14,"op":15,"st":14,"bm":0},{"ddd":0,"ind":20,"ty":4,"nm":"“图层 6”轮廓 9","sr":1,"ks":{"o":{"a":0,"k":100,"ix":11},"r":{"a":0,"k":0,"ix":10},"p":{"a":0,"k":[35.727,50.728,0],"ix":2},"a":{"a":0,"k":[33.976,48.522,0],"ix":1},"s":{"a":0,"k":[100,100,100],"ix":6}},"ao":0,"shapes":[{"ty":"gr","it":[{"ind":0,"ty":"sh","ix":1,"ks":{"a":0,"k":{"i":[[0,0],[0,0]],"o":[[0,0],[0,0]],"v":[[-24.12,-40.634],[-24.12,-40.589]],"c":true},"ix":2},"nm":"路径 1","mn":"ADBE Vector Shape - Group","hd":false},{"ind":1,"ty":"sh","ix":2,"ks":{"a":0,"k":{"i":[[0.761,0],[0.859,1.6],[9.767,-2.198],[0.889,0.03],[2.194,2.298],[-0.076,3.176],[0,0],[-4.205,0.05],[0,0],[-6.114,-6.842],[2.759,2.826],[6.348,0],[0.075,-0.001],[0,0],[0,0],[-0.254,-0.265],[-0.852,-0.019],[-0.175,0.036],[-7.223,-13.424],[2.317,-1.247]],"o":[[-1.699,0],[-6.43,-11.943],[-0.961,0.197],[-3.186,-0.076],[-2.192,-2.3],[0,0],[-0.049,-4.151],[0,0],[9.232,-0.035],[6.117,9.888],[-4.199,-4.699],[-0.075,0],[0,0],[0,0],[-0.021,0.962],[0.251,0.264],[0.179,-0.002],[18.266,-4.101],[1.247,2.318],[-0.717,0.387]],"v":[[14.112,48.272],[9.911,45.763],[-19.286,36.124],[-22.03,36.382],[-30.366,32.702],[-33.65,24.211],[-33.652,-40.574],[-26.117,-48.237],[-8.609,-48.237],[15.406,-37.616],[8.264,-31.304],[-8.334,-38.706],[-8.56,-38.705],[-24.12,-38.705],[-24.12,24.324],[-23.468,26.121],[-21.816,26.851],[-21.285,26.804],[18.303,41.246],[16.365,47.702]],"c":true},"ix":2},"nm":"路径 2","mn":"ADBE Vector Shape - Group","hd":false},{"ty":"mm","mm":1,"nm":"合并路径 1","mn":"ADBE Vector Filter - Merge","hd":false},{"ty":"fl","c":{"a":0,"k":[0,0,0,1],"ix":4},"o":{"a":0,"k":100,"ix":5},"r":1,"bm":0,"nm":"填充 1","mn":"ADBE Vector Graphic - Fill","hd":false},{"ty":"tr","p":{"a":0,"k":[33.976,48.522],"ix":2},"a":{"a":0,"k":[0,0],"ix":1},"s":{"a":0,"k":[100,100],"ix":3},"r":{"a":0,"k":0,"ix":6},"o":{"a":0,"k":100,"ix":7},"sk":{"a":0,"k":0,"ix":4},"sa":{"a":0,"k":0,"ix":5},"nm":"变换"}],"nm":"组 1","np":4,"cix":2,"bm":0,"ix":1,"mn":"ADBE Vector Group","hd":false}],"ip":13,"op":14,"st":13,"bm":0},{"ddd":0,"ind":21,"ty":4,"nm":"“图层 6”轮廓 8","sr":1,"ks":{"o":{"a":0,"k":100,"ix":11},"r":{"a":0,"k":0,"ix":10},"p":{"a":0,"k":[35.727,50.728,0],"ix":2},"a":{"a":0,"k":[33.976,48.522,0],"ix":1},"s":{"a":0,"k":[100,100,100],"ix":6}},"ao":0,"shapes":[{"ty":"gr","it":[{"ind":0,"ty":"sh","ix":1,"ks":{"a":0,"k":{"i":[[0,0],[0,0]],"o":[[0,0],[0,0]],"v":[[-24.12,-40.634],[-24.12,-40.589]],"c":true},"ix":2},"nm":"路径 1","mn":"ADBE Vector Shape - Group","hd":false},{"ind":1,"ty":"sh","ix":2,"ks":{"a":0,"k":{"i":[[0.761,0],[0.859,1.6],[9.767,-2.198],[0.889,0.03],[2.194,2.298],[-0.076,3.176],[0,0],[-4.205,0.05],[0,0],[6.348,0],[0.075,-0.001],[0,0],[0,0],[-0.254,-0.265],[-0.852,-0.019],[-0.175,0.036],[-7.223,-13.424],[2.317,-1.247]],"o":[[-1.699,0],[-6.43,-11.943],[-0.961,0.197],[-3.186,-0.076],[-2.192,-2.3],[0,0],[-0.049,-4.151],[0,0],[9.232,-0.035],[-0.075,0],[0,0],[0,0],[-0.021,0.962],[0.251,0.264],[0.179,-0.002],[18.266,-4.101],[1.247,2.318],[-0.717,0.387]],"v":[[14.112,48.272],[9.911,45.763],[-19.286,36.124],[-22.03,36.382],[-30.366,32.702],[-33.65,24.211],[-33.652,-40.574],[-26.117,-48.237],[-8.609,-48.237],[-8.334,-38.706],[-8.56,-38.705],[-24.12,-38.705],[-24.12,24.324],[-23.468,26.121],[-21.816,26.851],[-21.285,26.804],[18.303,41.246],[16.365,47.702]],"c":true},"ix":2},"nm":"路径 2","mn":"ADBE Vector Shape - Group","hd":false},{"ty":"mm","mm":1,"nm":"合并路径 1","mn":"ADBE Vector Filter - Merge","hd":false},{"ty":"fl","c":{"a":0,"k":[0,0,0,1],"ix":4},"o":{"a":0,"k":100,"ix":5},"r":1,"bm":0,"nm":"填充 1","mn":"ADBE Vector Graphic - Fill","hd":false},{"ty":"tr","p":{"a":0,"k":[33.976,48.522],"ix":2},"a":{"a":0,"k":[0,0],"ix":1},"s":{"a":0,"k":[100,100],"ix":3},"r":{"a":0,"k":0,"ix":6},"o":{"a":0,"k":100,"ix":7},"sk":{"a":0,"k":0,"ix":4},"sa":{"a":0,"k":0,"ix":5},"nm":"变换"}],"nm":"组 1","np":4,"cix":2,"bm":0,"ix":1,"mn":"ADBE Vector Group","hd":false}],"ip":12,"op":13,"st":12,"bm":0},{"ddd":0,"ind":22,"ty":4,"nm":"“图层 6”轮廓 7","sr":1,"ks":{"o":{"a":0,"k":100,"ix":11},"r":{"a":0,"k":0,"ix":10},"p":{"a":0,"k":[35.727,50.728,0],"ix":2},"a":{"a":0,"k":[33.976,48.522,0],"ix":1},"s":{"a":0,"k":[100,100,100],"ix":6}},"ao":0,"shapes":[{"ty":"gr","it":[{"ind":0,"ty":"sh","ix":1,"ks":{"a":0,"k":{"i":[[0,0],[0,0]],"o":[[0,0],[0,0]],"v":[[-24.12,-40.634],[-24.12,-40.589]],"c":true},"ix":2},"nm":"路径 1","mn":"ADBE Vector Shape - Group","hd":false},{"ind":1,"ty":"sh","ix":2,"ks":{"a":0,"k":{"i":[[0.761,0],[0.859,1.6],[9.767,-2.198],[0.889,0.03],[2.194,2.298],[-0.076,3.176],[0,0],[-4.205,0.05],[0,0],[0,0],[-0.254,-0.265],[-0.852,-0.019],[-0.175,0.036],[-7.223,-13.424],[2.317,-1.247]],"o":[[-1.699,0],[-6.43,-11.943],[-0.961,0.197],[-3.186,-0.076],[-2.192,-2.3],[0,0],[-0.049,-4.151],[0,0],[0,0],[-0.021,0.962],[0.251,0.264],[0.179,-0.002],[18.266,-4.101],[1.247,2.318],[-0.717,0.387]],"v":[[14.112,48.272],[9.911,45.763],[-19.286,36.124],[-22.03,36.382],[-30.366,32.702],[-33.65,24.211],[-33.652,-40.574],[-26.117,-48.237],[-24.12,-38.705],[-24.12,24.324],[-23.468,26.121],[-21.816,26.851],[-21.285,26.804],[18.303,41.246],[16.365,47.702]],"c":true},"ix":2},"nm":"路径 2","mn":"ADBE Vector Shape - Group","hd":false},{"ty":"mm","mm":1,"nm":"合并路径 1","mn":"ADBE Vector Filter - Merge","hd":false},{"ty":"fl","c":{"a":0,"k":[0,0,0,1],"ix":4},"o":{"a":0,"k":100,"ix":5},"r":1,"bm":0,"nm":"填充 1","mn":"ADBE Vector Graphic - Fill","hd":false},{"ty":"tr","p":{"a":0,"k":[33.976,48.522],"ix":2},"a":{"a":0,"k":[0,0],"ix":1},"s":{"a":0,"k":[100,100],"ix":3},"r":{"a":0,"k":0,"ix":6},"o":{"a":0,"k":100,"ix":7},"sk":{"a":0,"k":0,"ix":4},"sa":{"a":0,"k":0,"ix":5},"nm":"变换"}],"nm":"组 1","np":4,"cix":2,"bm":0,"ix":1,"mn":"ADBE Vector Group","hd":false}],"ip":11,"op":12,"st":11,"bm":0},{"ddd":0,"ind":23,"ty":4,"nm":"“图层 6”轮廓 6","sr":1,"ks":{"o":{"a":0,"k":100,"ix":11},"r":{"a":0,"k":0,"ix":10},"p":{"a":0,"k":[35.727,50.728,0],"ix":2},"a":{"a":0,"k":[33.976,48.522,0],"ix":1},"s":{"a":0,"k":[100,100,100],"ix":6}},"ao":0,"shapes":[{"ty":"gr","it":[{"ind":0,"ty":"sh","ix":1,"ks":{"a":0,"k":{"i":[[0,0],[0,0]],"o":[[0,0],[0,0]],"v":[[-24.12,-40.634],[-24.12,-40.589]],"c":true},"ix":2},"nm":"路径 1","mn":"ADBE Vector Shape - Group","hd":false},{"ind":1,"ty":"sh","ix":2,"ks":{"a":0,"k":{"i":[[0.761,0],[0.859,1.6],[9.767,-2.198],[0.889,0.03],[2.194,2.298],[-0.076,3.176],[0,0],[0,0],[0,0],[-0.254,-0.265],[-0.852,-0.019],[-0.175,0.036],[-7.223,-13.424],[2.317,-1.247]],"o":[[-1.699,0],[-6.43,-11.943],[-0.961,0.197],[-3.186,-0.076],[-2.192,-2.3],[0,0],[0,0],[0,0],[-0.021,0.962],[0.251,0.264],[0.179,-0.002],[18.266,-4.101],[1.247,2.318],[-0.717,0.387]],"v":[[14.112,48.272],[9.911,45.763],[-19.286,36.124],[-22.03,36.382],[-30.366,32.702],[-33.65,24.211],[-33.652,-24.728],[-24.12,-24.728],[-24.12,24.324],[-23.468,26.121],[-21.816,26.851],[-21.285,26.804],[18.303,41.246],[16.365,47.702]],"c":true},"ix":2},"nm":"路径 2","mn":"ADBE Vector Shape - Group","hd":false},{"ty":"mm","mm":1,"nm":"合并路径 1","mn":"ADBE Vector Filter - Merge","hd":false},{"ty":"fl","c":{"a":0,"k":[0,0,0,1],"ix":4},"o":{"a":0,"k":100,"ix":5},"r":1,"bm":0,"nm":"填充 1","mn":"ADBE Vector Graphic - Fill","hd":false},{"ty":"tr","p":{"a":0,"k":[33.976,48.522],"ix":2},"a":{"a":0,"k":[0,0],"ix":1},"s":{"a":0,"k":[100,100],"ix":3},"r":{"a":0,"k":0,"ix":6},"o":{"a":0,"k":100,"ix":7},"sk":{"a":0,"k":0,"ix":4},"sa":{"a":0,"k":0,"ix":5},"nm":"变换"}],"nm":"组 1","np":4,"cix":2,"bm":0,"ix":1,"mn":"ADBE Vector Group","hd":false}],"ip":10,"op":11,"st":10,"bm":0},{"ddd":0,"ind":24,"ty":4,"nm":"“图层 6”轮廓 5","sr":1,"ks":{"o":{"a":0,"k":100,"ix":11},"r":{"a":0,"k":0,"ix":10},"p":{"a":0,"k":[35.727,50.728,0],"ix":2},"a":{"a":0,"k":[33.976,48.522,0],"ix":1},"s":{"a":0,"k":[100,100,100],"ix":6}},"ao":0,"shapes":[{"ty":"gr","it":[{"ind":0,"ty":"sh","ix":1,"ks":{"a":0,"k":{"i":[[0,0],[0,0]],"o":[[0,0],[0,0]],"v":[[-24.12,-40.634],[-24.12,-40.589]],"c":true},"ix":2},"nm":"路径 1","mn":"ADBE Vector Shape - Group","hd":false},{"ind":1,"ty":"sh","ix":2,"ks":{"a":0,"k":{"i":[[0.761,0],[0.859,1.6],[9.767,-2.198],[0.889,0.03],[2.194,2.298],[-0.076,3.176],[0,0],[0,0],[0,0],[-0.254,-0.265],[-0.852,-0.019],[-0.175,0.036],[-7.223,-13.424],[2.317,-1.247]],"o":[[-1.699,0],[-6.43,-11.943],[-0.961,0.197],[-3.186,-0.076],[-2.192,-2.3],[0,0],[0,0],[0,0],[-0.021,0.962],[0.251,0.264],[0.179,-0.002],[18.266,-4.101],[1.247,2.318],[-0.717,0.387]],"v":[[14.112,48.272],[9.911,45.763],[-19.286,36.124],[-22.03,36.382],[-30.366,32.702],[-33.65,24.211],[-33.651,-7.728],[-24.12,-7.478],[-24.12,24.324],[-23.468,26.121],[-21.816,26.851],[-21.285,26.804],[18.303,41.246],[16.365,47.702]],"c":true},"ix":2},"nm":"路径 2","mn":"ADBE Vector Shape - Group","hd":false},{"ty":"mm","mm":1,"nm":"合并路径 1","mn":"ADBE Vector Filter - Merge","hd":false},{"ty":"fl","c":{"a":0,"k":[0,0,0,1],"ix":4},"o":{"a":0,"k":100,"ix":5},"r":1,"bm":0,"nm":"填充 1","mn":"ADBE Vector Graphic - Fill","hd":false},{"ty":"tr","p":{"a":0,"k":[33.976,48.522],"ix":2},"a":{"a":0,"k":[0,0],"ix":1},"s":{"a":0,"k":[100,100],"ix":3},"r":{"a":0,"k":0,"ix":6},"o":{"a":0,"k":100,"ix":7},"sk":{"a":0,"k":0,"ix":4},"sa":{"a":0,"k":0,"ix":5},"nm":"变换"}],"nm":"组 1","np":4,"cix":2,"bm":0,"ix":1,"mn":"ADBE Vector Group","hd":false}],"ip":9,"op":10,"st":9,"bm":0},{"ddd":0,"ind":25,"ty":4,"nm":"“图层 6”轮廓 4","sr":1,"ks":{"o":{"a":0,"k":100,"ix":11},"r":{"a":0,"k":0,"ix":10},"p":{"a":0,"k":[35.727,50.728,0],"ix":2},"a":{"a":0,"k":[33.976,48.522,0],"ix":1},"s":{"a":0,"k":[100,100,100],"ix":6}},"ao":0,"shapes":[{"ty":"gr","it":[{"ind":0,"ty":"sh","ix":1,"ks":{"a":0,"k":{"i":[[0,0],[0,0]],"o":[[0,0],[0,0]],"v":[[-24.12,-40.634],[-24.12,-40.589]],"c":true},"ix":2},"nm":"路径 1","mn":"ADBE Vector Shape - Group","hd":false},{"ind":1,"ty":"sh","ix":2,"ks":{"a":0,"k":{"i":[[0.761,0],[0.859,1.6],[9.767,-2.198],[0.889,0.03],[2.194,2.298],[-0.076,3.176],[0,0],[0,0],[0,0],[-0.254,-0.265],[-0.852,-0.019],[-0.175,0.036],[-7.223,-13.424],[2.317,-1.247]],"o":[[-1.699,0],[-6.43,-11.943],[-0.961,0.197],[-3.186,-0.076],[-2.192,-2.3],[0,0],[0,0],[0,0],[-0.021,0.962],[0.251,0.264],[0.179,-0.002],[18.266,-4.101],[1.247,2.318],[-0.717,0.387]],"v":[[14.112,48.272],[9.911,45.763],[-19.286,36.124],[-22.03,36.382],[-30.366,32.702],[-33.65,24.211],[-33.4,9.022],[-24.12,9.522],[-24.12,24.324],[-23.468,26.121],[-21.816,26.851],[-21.285,26.804],[18.303,41.246],[16.365,47.702]],"c":true},"ix":2},"nm":"路径 2","mn":"ADBE Vector Shape - Group","hd":false},{"ty":"mm","mm":1,"nm":"合并路径 1","mn":"ADBE Vector Filter - Merge","hd":false},{"ty":"fl","c":{"a":0,"k":[0,0,0,1],"ix":4},"o":{"a":0,"k":100,"ix":5},"r":1,"bm":0,"nm":"填充 1","mn":"ADBE Vector Graphic - Fill","hd":false},{"ty":"tr","p":{"a":0,"k":[33.976,48.522],"ix":2},"a":{"a":0,"k":[0,0],"ix":1},"s":{"a":0,"k":[100,100],"ix":3},"r":{"a":0,"k":0,"ix":6},"o":{"a":0,"k":100,"ix":7},"sk":{"a":0,"k":0,"ix":4},"sa":{"a":0,"k":0,"ix":5},"nm":"变换"}],"nm":"组 1","np":4,"cix":2,"bm":0,"ix":1,"mn":"ADBE Vector Group","hd":false}],"ip":8,"op":9,"st":8,"bm":0},{"ddd":0,"ind":26,"ty":4,"nm":"“图层 6”轮廓 3","sr":1,"ks":{"o":{"a":0,"k":100,"ix":11},"r":{"a":0,"k":0,"ix":10},"p":{"a":0,"k":[35.727,50.728,0],"ix":2},"a":{"a":0,"k":[33.976,48.522,0],"ix":1},"s":{"a":0,"k":[100,100,100],"ix":6}},"ao":0,"shapes":[{"ty":"gr","it":[{"ind":0,"ty":"sh","ix":1,"ks":{"a":0,"k":{"i":[[0,0],[0,0]],"o":[[0,0],[0,0]],"v":[[-24.12,-40.634],[-24.12,-40.589]],"c":true},"ix":2},"nm":"路径 1","mn":"ADBE Vector Shape - Group","hd":false},{"ind":1,"ty":"sh","ix":2,"ks":{"a":0,"k":{"i":[[0.761,0],[0.859,1.6],[9.767,-2.198],[0.889,0.03],[2.194,2.298],[-0.076,3.176],[0,0],[-0.254,-0.265],[-0.852,-0.019],[-0.175,0.036],[-7.223,-13.424],[2.317,-1.247]],"o":[[-1.699,0],[-6.43,-11.943],[-0.961,0.197],[-3.186,-0.076],[-2.192,-2.3],[0,0],[-0.021,0.962],[0.251,0.264],[0.179,-0.002],[18.266,-4.101],[1.247,2.318],[-0.717,0.387]],"v":[[14.112,48.272],[9.911,45.763],[-19.286,36.124],[-22.03,36.382],[-30.366,32.702],[-33.65,24.211],[-24.12,24.324],[-23.468,26.121],[-21.816,26.851],[-21.285,26.804],[18.303,41.246],[16.365,47.702]],"c":true},"ix":2},"nm":"路径 2","mn":"ADBE Vector Shape - Group","hd":false},{"ty":"mm","mm":1,"nm":"合并路径 1","mn":"ADBE Vector Filter - Merge","hd":false},{"ty":"fl","c":{"a":0,"k":[0,0,0,1],"ix":4},"o":{"a":0,"k":100,"ix":5},"r":1,"bm":0,"nm":"填充 1","mn":"ADBE Vector Graphic - Fill","hd":false},{"ty":"tr","p":{"a":0,"k":[33.976,48.522],"ix":2},"a":{"a":0,"k":[0,0],"ix":1},"s":{"a":0,"k":[100,100],"ix":3},"r":{"a":0,"k":0,"ix":6},"o":{"a":0,"k":100,"ix":7},"sk":{"a":0,"k":0,"ix":4},"sa":{"a":0,"k":0,"ix":5},"nm":"变换"}],"nm":"组 1","np":4,"cix":2,"bm":0,"ix":1,"mn":"ADBE Vector Group","hd":false}],"ip":7,"op":8,"st":7,"bm":0},{"ddd":0,"ind":27,"ty":4,"nm":"“图层 6”轮廓 2","sr":1,"ks":{"o":{"a":0,"k":100,"ix":11},"r":{"a":0,"k":0,"ix":10},"p":{"a":0,"k":[35.727,50.728,0],"ix":2},"a":{"a":0,"k":[33.976,48.522,0],"ix":1},"s":{"a":0,"k":[100,100,100],"ix":6}},"ao":0,"shapes":[{"ty":"gr","it":[{"ind":0,"ty":"sh","ix":1,"ks":{"a":0,"k":{"i":[[0,0],[0,0]],"o":[[0,0],[0,0]],"v":[[-24.12,-40.634],[-24.12,-40.589]],"c":true},"ix":2},"nm":"路径 1","mn":"ADBE Vector Shape - Group","hd":false},{"ind":1,"ty":"sh","ix":2,"ks":{"a":0,"k":{"i":[[0.761,0],[0.859,1.6],[5.592,1.063],[-5.413,-0.905],[-4.595,-8.539],[2.317,-1.247]],"o":[[-1.699,0],[-3.383,-6.283],[-5.038,-0.958],[9.462,1.583],[1.247,2.318],[-0.717,0.387]],"v":[[14.112,48.272],[9.911,45.763],[-4.264,35.469],[-3.13,25.946],[18.303,41.246],[16.365,47.702]],"c":true},"ix":2},"nm":"路径 2","mn":"ADBE Vector Shape - Group","hd":false},{"ty":"mm","mm":1,"nm":"合并路径 1","mn":"ADBE Vector Filter - Merge","hd":false},{"ty":"fl","c":{"a":0,"k":[0,0,0,1],"ix":4},"o":{"a":0,"k":100,"ix":5},"r":1,"bm":0,"nm":"填充 1","mn":"ADBE Vector Graphic - Fill","hd":false},{"ty":"tr","p":{"a":0,"k":[33.976,48.522],"ix":2},"a":{"a":0,"k":[0,0],"ix":1},"s":{"a":0,"k":[100,100],"ix":3},"r":{"a":0,"k":0,"ix":6},"o":{"a":0,"k":100,"ix":7},"sk":{"a":0,"k":0,"ix":4},"sa":{"a":0,"k":0,"ix":5},"nm":"变换"}],"nm":"组 1","np":4,"cix":2,"bm":0,"ix":1,"mn":"ADBE Vector Group","hd":false}],"ip":6,"op":7,"st":6,"bm":0},{"ddd":0,"ind":28,"ty":4,"nm":"“图层 6”轮廓","sr":1,"ks":{"o":{"a":0,"k":100,"ix":11},"r":{"a":0,"k":0,"ix":10},"p":{"a":0,"k":[35.727,50.728,0],"ix":2},"a":{"a":0,"k":[33.976,48.522,0],"ix":1},"s":{"a":0,"k":[100,100,100],"ix":6}},"ao":0,"shapes":[{"ty":"gr","it":[{"ind":0,"ty":"sh","ix":1,"ks":{"a":0,"k":{"i":[[0,0],[0,0]],"o":[[0,0],[0,0]],"v":[[-24.12,-40.634],[-24.12,-40.589]],"c":true},"ix":2},"nm":"路径 1","mn":"ADBE Vector Shape - Group","hd":false},{"ind":1,"ty":"sh","ix":2,"ks":{"a":0,"k":{"i":[[0.761,0],[0.859,1.6],[2.184,1.619],[-7.861,-6.774],[-1.851,-3.44],[2.317,-1.247]],"o":[[-1.699,0],[-1.554,-2.887],[-6.85,-5.08],[2.708,2.334],[1.247,2.318],[-0.717,0.387]],"v":[[14.112,48.272],[9.911,45.763],[4.235,39.074],[11.441,32.577],[18.303,41.246],[16.365,47.702]],"c":true},"ix":2},"nm":"路径 2","mn":"ADBE Vector Shape - Group","hd":false},{"ty":"mm","mm":1,"nm":"合并路径 1","mn":"ADBE Vector Filter - Merge","hd":false},{"ty":"fl","c":{"a":0,"k":[0,0,0,1],"ix":4},"o":{"a":0,"k":100,"ix":5},"r":1,"bm":0,"nm":"填充 1","mn":"ADBE Vector Graphic - Fill","hd":false},{"ty":"tr","p":{"a":0,"k":[33.976,48.522],"ix":2},"a":{"a":0,"k":[0,0],"ix":1},"s":{"a":0,"k":[100,100],"ix":3},"r":{"a":0,"k":0,"ix":6},"o":{"a":0,"k":100,"ix":7},"sk":{"a":0,"k":0,"ix":4},"sa":{"a":0,"k":0,"ix":5},"nm":"变换"}],"nm":"组 1","np":4,"cix":2,"bm":0,"ix":1,"mn":"ADBE Vector Group","hd":false}],"ip":5,"op":6,"st":5,"bm":0},{"ddd":0,"ind":29,"ty":4,"nm":"“图层 7”轮廓","sr":1,"ks":{"o":{"a":0,"k":100,"ix":11},"r":{"a":0,"k":0,"ix":10},"p":{"a":0,"k":[50.341,50.727,0],"ix":2},"a":{"a":0,"k":[48.59,48.522,0],"ix":1},"s":{"a":0,"k":[100,100,100],"ix":6}},"ao":0,"shapes":[{"ty":"gr","it":[{"ind":0,"ty":"sh","ix":1,"ks":{"a":0,"k":{"i":[[0,0],[0,0]],"o":[[0,0],[0,0]],"v":[[24.499,-40.555],[24.499,-40.523]],"c":true},"ix":2},"nm":"路径 1","mn":"ADBE Vector Shape - Group","hd":false},{"ind":1,"ty":"sh","ix":2,"ks":{"a":0,"k":{"i":[[1.687,0],[0.726,0.396],[-1.261,2.312],[-18.557,-4.109],[-0.193,-0.006],[0.021,1.339],[0,0],[0,0],[4.562,-5.564],[0.02,-0.288],[2.635,0.185],[-0.186,2.623],[-14.61,18.07],[-10.2,-0.033],[0,0],[0.037,-4.213],[0,0],[6.593,-0.101],[0.855,0.181],[6.53,-11.972]],"o":[[-0.77,0],[-2.311,-1.261],[7.308,-13.4],[0.121,0.026],[1.328,-0.019],[0,0],[0,0],[-7.192,-0.062],[-12.692,15.697],[-0.191,2.623],[-2.625,-0.186],[0.093,-1.296],[6.414,-7.823],[0,0],[4.266,0.047],[0,0],[0.096,6.522],[-0.873,-0.013],[-9.991,-2.211],[-0.865,1.587]],"v":[[-14.309,48.271],[-16.588,47.688],[-18.49,41.221],[21.628,26.818],[22.117,26.859],[24.499,24.393],[24.499,-38.705],[9.009,-38.705],[-9.519,-30.027],[-24.432,14.613],[-29.527,19.025],[-33.941,13.936],[-16.911,-36.044],[9.039,-48.238],[26.406,-48.238],[34.031,-40.512],[34.031,24.322],[22.251,36.391],[19.615,36.135],[-10.12,45.785]],"c":true},"ix":2},"nm":"路径 2","mn":"ADBE Vector Shape - Group","hd":false},{"ty":"mm","mm":1,"nm":"合并路径 1","mn":"ADBE Vector Filter - Merge","hd":false},{"ty":"fl","c":{"a":0,"k":[0.823999980852,0.819999964097,0.830999995213,1],"ix":4},"o":{"a":0,"k":100,"ix":5},"r":1,"bm":0,"nm":"填充 1","mn":"ADBE Vector Graphic - Fill","hd":false},{"ty":"tr","p":{"a":0,"k":[62.802,48.522],"ix":2},"a":{"a":0,"k":[0,0],"ix":1},"s":{"a":0,"k":[100,100],"ix":3},"r":{"a":0,"k":0,"ix":6},"o":{"a":0,"k":100,"ix":7},"sk":{"a":0,"k":0,"ix":4},"sa":{"a":0,"k":0,"ix":5},"nm":"变换"}],"nm":"组 1","np":4,"cix":2,"bm":0,"ix":1,"mn":"ADBE Vector Group","hd":false},{"ty":"gr","it":[{"ind":0,"ty":"sh","ix":1,"ks":{"a":0,"k":{"i":[[2.632,0],[0,0],[0,2.632],[-2.633,0],[0,0],[0,-2.631]],"o":[[0,0],[-2.633,0],[0,-2.631],[0,0],[2.632,0],[0,2.632]],"v":[[12.12,4.766],[-12.12,4.766],[-16.887,-0.001],[-12.12,-4.766],[12.12,-4.766],[16.887,-0.001]],"c":true},"ix":2},"nm":"路径 1","mn":"ADBE Vector Shape - Group","hd":false},{"ty":"fl","c":{"a":0,"k":[0.823999980852,0.819999964097,0.830999995213,1],"ix":4},"o":{"a":0,"k":100,"ix":5},"r":1,"bm":0,"nm":"填充 1","mn":"ADBE Vector Graphic - Fill","hd":false},{"ty":"tr","p":{"a":0,"k":[48.368,46.981],"ix":2},"a":{"a":0,"k":[0,0],"ix":1},"s":{"a":0,"k":[100,100],"ix":3},"r":{"a":0,"k":0,"ix":6},"o":{"a":0,"k":100,"ix":7},"sk":{"a":0,"k":0,"ix":4},"sa":{"a":0,"k":0,"ix":5},"nm":"变换"}],"nm":"组 2","np":2,"cix":2,"bm":0,"ix":2,"mn":"ADBE Vector Group","hd":false},{"ty":"gr","it":[{"ind":0,"ty":"sh","ix":1,"ks":{"a":0,"k":{"i":[[0,0],[0,0]],"o":[[0,0],[0,0]],"v":[[-24.12,-40.634],[-24.12,-40.589]],"c":true},"ix":2},"nm":"路径 1","mn":"ADBE Vector Shape - Group","hd":false},{"ind":1,"ty":"sh","ix":2,"ks":{"a":0,"k":{"i":[[0.761,0],[0.859,1.6],[9.767,-2.198],[0.889,0.03],[2.194,2.298],[-0.076,3.176],[0,0],[-4.205,0.05],[0,0],[-6.114,-6.842],[-0.095,-1.368],[2.623,-0.186],[0.188,2.624],[13.447,15.384],[6.348,0],[0.075,-0.001],[0,0],[0,0],[-0.254,-0.265],[-0.852,-0.019],[-0.175,0.036],[-7.223,-13.424],[2.317,-1.247]],"o":[[-1.699,0],[-6.43,-11.943],[-0.961,0.197],[-3.186,-0.076],[-2.192,-2.3],[0,0],[-0.049,-4.151],[0,0],[9.232,-0.035],[15.604,17.849],[0.184,2.625],[-2.693,0.201],[-0.021,-0.303],[-4.199,-4.699],[-0.075,0],[0,0],[0,0],[-0.021,0.962],[0.251,0.264],[0.179,-0.002],[18.266,-4.101],[1.247,2.318],[-0.717,0.387]],"v":[[14.112,48.272],[9.911,45.763],[-19.286,36.124],[-22.03,36.382],[-30.366,32.702],[-33.65,24.211],[-33.652,-40.574],[-26.117,-48.237],[-8.609,-48.237],[15.406,-37.616],[33.542,13.937],[29.125,19.025],[24.033,14.607],[8.264,-31.304],[-8.334,-38.706],[-8.56,-38.705],[-24.12,-38.705],[-24.12,24.324],[-23.468,26.121],[-21.816,26.851],[-21.285,26.804],[18.303,41.246],[16.365,47.702]],"c":true},"ix":2},"nm":"路径 2","mn":"ADBE Vector Shape - Group","hd":false},{"ty":"mm","mm":1,"nm":"合并路径 1","mn":"ADBE Vector Filter - Merge","hd":false},{"ty":"fl","c":{"a":0,"k":[0.823999980852,0.819999964097,0.830999995213,1],"ix":4},"o":{"a":0,"k":100,"ix":5},"r":1,"bm":0,"nm":"填充 1","mn":"ADBE Vector Graphic - Fill","hd":false},{"ty":"tr","p":{"a":0,"k":[33.976,48.523],"ix":2},"a":{"a":0,"k":[0,0],"ix":1},"s":{"a":0,"k":[100,100],"ix":3},"r":{"a":0,"k":0,"ix":6},"o":{"a":0,"k":100,"ix":7},"sk":{"a":0,"k":0,"ix":4},"sa":{"a":0,"k":0,"ix":5},"nm":"变换"}],"nm":"组 3","np":4,"cix":2,"bm":0,"ix":3,"mn":"ADBE Vector Group","hd":false}],"ip":0,"op":50,"st":0,"bm":0},{"ddd":0,"ind":30,"ty":4,"nm":"形状图层 1","sr":1,"ks":{"o":{"a":0,"k":100,"ix":11},"r":{"a":0,"k":0,"ix":10},"p":{"a":0,"k":[50,50,0],"ix":2},"a":{"a":0,"k":[0,0,0],"ix":1},"s":{"a":0,"k":[100,100,100],"ix":6}},"ao":0,"shapes":[{"ty":"gr","it":[{"ind":0,"ty":"sh","ix":1,"ks":{"a":0,"k":{"i":[[0,0],[0,0],[0,0],[-7.5,1.25],[-2.25,3.25],[0,0]],"o":[[0,0],[0,0],[0,0],[21.545,-3.591],[2.25,-3.25],[0,0]],"v":[[40.75,-41],[1,-35.5],[-40.5,-41],[-39,32],[2,39.75],[39.75,29]],"c":true},"ix":2},"nm":"路径 1","mn":"ADBE Vector Shape - Group","hd":false},{"ty":"gf","o":{"a":0,"k":100,"ix":10},"r":1,"bm":0,"g":{"p":2,"k":{"a":0,"k":[0,1,0.670,0.101,1,1,1,1],"ix":9}},"s":{"a":1,"k":[{"i":{"x":0.833,"y":0.833},"o":{"x":0.167,"y":0.167},"t":15,"s":[40.75,-0.25],"to":[0,0],"ti":[0,0]},{"i":{"x":0.833,"y":0.833},"o":{"x":0.167,"y":0.167},"t":20,"s":[40.75,-0.25],"to":[0,0],"ti":[0,0]},{"i":{"x":0.833,"y":0.833},"o":{"x":0.167,"y":0.167},"t":27,"s":[40.75,-0.25],"to":[0,0],"ti":[0,0]},{"i":{"x":0.833,"y":0.833},"o":{"x":0.167,"y":0.167},"t":30,"s":[40.75,-0.25],"to":[0,0],"ti":[0,0]},{"t":35,"s":[40.75,-0.25]}],"ix":5},"e":{"a":1,"k":[{"i":{"x":0.833,"y":0.833},"o":{"x":0.167,"y":0.167},"t":15,"s":[38.85,-0.4],"to":[-25.241,0.103],"ti":[13.6,-0.067]},{"i":{"x":0.833,"y":0.833},"o":{"x":0.167,"y":0.167},"t":20,"s":[-112.598,0.217],"to":[0,0],"ti":[13.6,-0.067]},{"i":{"x":0.833,"y":0.833},"o":{"x":0.167,"y":0.167},"t":27,"s":[-112.598,0.217],"to":[0,0],"ti":[0,0]},{"i":{"x":0.833,"y":0.833},"o":{"x":0.167,"y":0.167},"t":30,"s":[-42.75,0],"to":[13.6,-0.067],"ti":[-13.6,0.067]},{"t":35,"s":[38.85,-0.4]}],"ix":6},"t":1,"nm":"渐变填充 1","mn":"ADBE Vector Graphic - G-Fill","hd":false},{"ty":"tr","p":{"a":0,"k":[0,0],"ix":2},"a":{"a":0,"k":[0,0],"ix":1},"s":{"a":0,"k":[100,100],"ix":3},"r":{"a":0,"k":0,"ix":6},"o":{"a":0,"k":100,"ix":7},"sk":{"a":0,"k":0,"ix":4},"sa":{"a":0,"k":0,"ix":5},"nm":"变换"}],"nm":"形状 1","np":3,"cix":2,"bm":0,"ix":1,"mn":"ADBE Vector Group","hd":false}],"ip":15,"op":36,"st":15,"bm":0}],"markers":[]}